Workbook

Sheet Cronograma
A1: Fase CRISP-DM | B1: Fase del Charter | C1: Tarea | D1: Responsable | E1: Colaborador(es) | F1: Entregable | G1: Artefacto (archivo/formato) | H1: Fecha inicio | I1: Fecha fin | J1: Duración (días)
A2: Comprensión del Negocio / Datos | B2: Fase 1 | C2: Revisar y validar objetivos y alcance del Business Case | D2: Chicata | E2: Todo el equipo | F2: Business Case validado | G2: Business_Case_v2_aprobado.docx | H2: 46280 | I2: 46283 | J2: =I2-H2+1 -> 4
A3: Comprensión del Negocio / Datos | B3: Fase 1 | C3: Explorar estructura y diccionario de datos (HomeCredit_columns_description) | D3: De la Cruz | E3: Bayona, Chicata | F3: Diccionario de datos anotado | G3: diccionario_datos_anotado.xlsx | H3: 46281 | I3: 46284 | J3: =I3-H3+1 -> 4
A4: Comprensión del Negocio / Datos | B4: Fase 1 | C4: Calcular estadísticas descriptivas iniciales (TARGET, tasa de mora) | D4: De la Cruz | E4: Chicata | F4: Reporte de EDA inicial | G4: eda_inicial.ipynb + reporte_eda_inicial.pdf | H4: 46282 | I4: 46285 | J4: =I4-H4+1 -> 4
A5: Comprensión del Negocio / Datos | B5: Fase 1 | C5: Crear y configurar el repositorio del proyecto | D5: Chicata | E5: Arevalo | F5: Repositorio Git creado (dueño/administrador: S. Chicata); configuración técnica a cargo de Arevalo | G5: repositorio_grupo12 (GitHub, dueño: S. Chicata) + requirements.txt | H5: 46280 | I5: 46284 | J5: =I5-H5+1 -> 5
A6: Comprensión del Negocio / Datos | B6: Fase 1 | C6: Identificar variables sensibles y riesgos de sesgo/cumplimiento | D6: Bayona | E6: - | F6: Lista preliminar de variables sensibles | G6: lista_variables_sensibles.xlsx | H6: 46283 | I6: 46287 | J6: =I6-H6+1 -> 5
A7: Preparación de los Datos | B7: Fase 2 | C7: Definir estrategia de lectura por bloques y tipos de datos reducidos | D7: Arevalo | E7: De la Cruz | F7: Script de carga optimizada | G7: load_data.py | H7: 46288 | I7: 46290 | J7: =I7-H7+1 -> 3
A8: Preparación de los Datos | B8: Fase 2 | C8: Limpieza de application_train (faltantes, outliers) | D8: De la Cruz | E8: Chicata | F8: Dataset limpio v1 | G8: application_train_clean.parquet | H8: 46289 | I8: 46295 | J8: =I8-H8+1 -> 7
A9: Preparación de los Datos | B9: Fase 2 | C9: Imputación de valores faltantes según diccionario | D9: De la Cruz | E9: Bayona, Chicata | F9: Reporte de imputación | G9: application_train_imputed.parquet + reporte_imputacion.pdf | H9: 46291 | I9: 46296 | J9: =I9-H9+1 -> 6
A10: Preparación de los Datos | B10: Fase 2 | C10: Preprocesamiento de bureau y bureau_balance (agregación en 2 niveles) | D10: Arevalo | E10: De la Cruz | F10: Tabla bureau agregada por cliente | G10: bureau_agg.parquet | H10: 46290 | I10: 46297 | J10: =I10-H10+1 -> 8
A11: Preparación de los Datos | B11: Fase 2 | C11: Preprocesamiento de previous_application y POS_CASH_balance | D11: Piñarreta | E11: De la Cruz | F11: Tablas agregadas por cliente | G11: previous_pos_agg.parquet | H11: 46292 | I11: 46298 | J11: =I11-H11+1 -> 7
A12: Preparación de los Datos | B12: Fase 2 | C12: Preprocesamiento de credit_card_balance e installments_payments | D12: Piñarreta | E12: De la Cruz | F12: Tablas agregadas por cliente | G12: cc_installments_agg.parquet | H12: 46293 | I12: 46299 | J12: =I12-H12+1 -> 7
A13: Preparación de los Datos | B13: Fase 2 | C13: Validar ausencia de leakage antes de separar train/validación | D13: Bayona | E13: De la Cruz | F13: Checklist de validación de leakage | G13: checklist_leakage.xlsx | H13: 46297 | I13: 46301 | J13: =I13-H13+1 -> 5
... A43: Cierre del proyecto | B43: Fase 7 | C43: Entrega final del proyecto | D43: Chicata | E43: Todo el equipo | F43: Entrega en la plataforma del curso | G43: paquete_entrega_final.zip | H43: 46364 | I43: 46364 | J43: =I43-H43+1 -> 1

Sheet Resumen por Integrante
A1: Integrante | B1: Rol en el Charter | C1: Tareas como Responsable | D1: Tareas como Colaborador | E1: Total de participaciones
A2: Chicata | B2: Gerente del Proyecto / Dueño del repositorio | C2: =COUNTIF(Cronograma!$D$2:$D$43,A2) -> 5 | D2: =COUNTIF(Cronograma!$E$2:$E$43,"*"&A2&"*") -> 15 | E2: =C2+D2 -> 20
A3: De la Cruz | B3: Equipo de Ciencia de Datos | C3: =COUNTIF(Cronograma!$D$2:$D$43,A3) -> 15 | D3: =COUNTIF(Cronograma!$E$2:$E$43,"*"&A3&"*") -> 12 | E3: =C3+D3 -> 27
A4: Arevalo | B4: Área de TI | C4: =COUNTIF(Cronograma!$D$2:$D$43,A4) -> 6 | D4: =COUNTIF(Cronograma!$E$2:$E$43,"*"&A4&"*") -> 4 | E4: =C4+D4 -> 10
A5: Piñarreta | B5: Equipo Backend/DevOps | C5: =COUNTIF(Cronograma!$D$2:$D$43,A5) -> 7 | D5: =COUNTIF(Cronograma!$E$2:$E$43,"*"&A5&"*") -> 5 | E5: =C5+D5 -> 12
A6: Bayona | B6: Riesgos y Cumplimiento | C6: =COUNTIF(Cronograma!$D$2:$D$43,A6) -> 8 | D6: =COUNTIF(Cronograma!$E$2:$E$43,"*"&A6&"*") -> 5 | E6: =C6+D6 -> 13
A8: Nota: 'Tareas como Colaborador' cuenta coincidencias de texto en la columna Colaborador(es), incluidas las celdas con varios nombres separados por coma. No incluye las filas marcadas como 'Todo el equipo'.
